IHEWAwapor/__init__.py
IHEWAwapor/WPdownload/AET_dekadal.py
IHEWAwapor/WPdownload/AET_monthly.py
IHEWAwapor/WPdownload/AET_yearly.py
IHEWAwapor/WPdownload/I_yearly.py
IHEWAwapor/WPdownload/LCC_yearly.py
IHEWAwapor/WPdownload/NPP_dekadal.py
IHEWAwapor/WPdownload/PCP_daily.py
IHEWAwapor/WPdownload/PCP_monthly.py
IHEWAwapor/WPdownload/PCP_yearly.py
IHEWAwapor/WPdownload/RET_monthly.py
IHEWAwapor/WPdownload/RET_yearly.py
IHEWAwapor/WPdownload/__init__.py
IHEWAwapor/WPdownload/token-example.yml
IHEWAwapor/WPdownload/download/GIS_functions.py
IHEWAwapor/WPdownload/download/WaporAPI.py
IHEWAwapor/WPdownload/download/__init__.py
IHEWAwapor-0.0.2.dist-info/AUTHORS.rst
IHEWAwapor-0.0.2.dist-info/LICENSE.rst
IHEWAwapor-0.0.2.dist-info/METADATA
IHEWAwapor-0.0.2.dist-info/WHEEL
IHEWAwapor-0.0.2.dist-info/top_level.txt
IHEWAwapor-0.0.2.dist-info/RECORD
