Metadata-Version: 2.1
Name: IHEWAwapor
Version: 0.0.2
Summary: IHE WaterAccounting WaPOR Download Tools
Home-page: https://github.com/wateraccounting/IHEWAwapor
Author: Quan Pan
Author-email: quanpan302@hotmail.com
License: GPLv3
Project-URL: Documentation, https://ihewawapor.readthedocs.io/en/latest/
Keywords: GDAL,Water
Platform: any
Classifier: Development Status :: 4 - Beta
Classifier: Programming Language :: Python :: 3
Classifier: Programming Language :: Python :: 3.5
Classifier: Programming Language :: Python :: 3.6
Classifier: Programming Language :: Python :: 3.7
Requires-Python: >=3.5
Requires-Dist: numpy
Requires-Dist: pandas
Requires-Dist: psutil
Requires-Dist: requests
Provides-Extra: testing
Requires-Dist: pytest ; extra == 'testing'
Requires-Dist: pytest-cov ; extra == 'testing'
